Metadata-Version: 1.0
Name: dist-al
Version: 0.0
Summary: Gaussian and Binomial distributions
Home-page: UNKNOWN
Author: UNKNOWN
Author-email: mihajlovic.aleksa@gmail.com
License: UNKNOWN
Platform: UNKNOWN
